goggles/__init__.py
goggles/config.py
goggles/media.py
goggles/shutdown.py
goggles/types.py
goggles/validation.py
goggles/_core/decorators.py
goggles/_core/logger.py
goggles/_core/routing.py
goggles/_core/integrations/__init__.py
goggles/_core/integrations/console.py
goggles/_core/integrations/storage.py
goggles/_core/integrations/wandb.py
goggles/history/__init__.py
goggles/history/buffer.py
goggles/history/spec.py
goggles/history/types.py
goggles/history/utils.py
robo_goggles-0.1.9.dist-info/licenses/LICENSE
robo_goggles-0.1.9.dist-info/METADATA
robo_goggles-0.1.9.dist-info/WHEEL
robo_goggles-0.1.9.dist-info/top_level.txt
robo_goggles-0.1.9.dist-info/RECORD
