Metadata-Version: 2.4
Name: robo-goggles
Version: 0.1.9
Summary: Observability framework for robotics research
Author-email: Antonio Terpin <aterpin@ethz.ch>, Francesco Banelli <fbanelli@ethz.ch>
License: MIT
Project-URL: Homepage, https://github.com/antonioterpin/goggles
Project-URL: Repository, https://github.com/antonioterpin/goggles
Project-URL: Documentation, https://github.com/antonioterpin/goggles#readme
Project-URL: Issues, https://github.com/antonioterpin/goggles/issues
Keywords: robotics,logging,observability,jax,wandb,experiment-tracking
Classifier: Development Status :: 4 - Beta
Classifier: Intended Audience :: Science/Research
Classifier: Intended Audience :: Developers
Classifier: License :: OSI Approved :: MIT License
Classifier: Operating System :: OS Independent
Classifier: Programming Language :: Python :: 3
Classifier: Programming Language :: Python :: 3.10
Classifier: Programming Language :: Python :: 3.11
Classifier: Programming Language :: Python :: 3.12
Classifier: Topic :: Scientific/Engineering :: Artificial Intelligence
Classifier: Topic :: System :: Logging
Requires-Python: >=3.10
License-File: LICENSE
Requires-Dist: ruamel.yaml
Requires-Dist: rich
Requires-Dist: portal>=3.7.3
Requires-Dist: typing-extensions>=4.15.0
Requires-Dist: netifaces>=0.11.0
Requires-Dist: pyyaml>=6.0.3
Requires-Dist: numpy>=1.23
Requires-Dist: imageio>=2.37.0
Requires-Dist: matplotlib>=3.10.7
Provides-Extra: dev
Requires-Dist: pytest>=7.0.0; extra == "dev"
Requires-Dist: pytest-cov>=4.0.0; extra == "dev"
Requires-Dist: pytest-xdist>=3.0.0; extra == "dev"
Requires-Dist: hypothesis>=6.0.0; extra == "dev"
Requires-Dist: snowballstemmer==2.2.0; extra == "dev"
Requires-Dist: pre_commit==4.0.1; extra == "dev"
Requires-Dist: tomli; extra == "dev"
Requires-Dist: pyupgrade>=3.19.0; extra == "dev"
Requires-Dist: psutil; extra == "dev"
Provides-Extra: jax
Requires-Dist: jax>=0.4.0; extra == "jax"
Requires-Dist: jaxlib>=0.4.0; extra == "jax"
Provides-Extra: wandb
Requires-Dist: wandb[media]; extra == "wandb"
Dynamic: license-file
